{
  "patterns": {
    "q1": {
      "hint": "入口はトラフィックを受けるLB、APIの窓口はゲートウェイ、隔離ネットワークはVPC、処理本体はVM/インスタンス、バイナリやファイル置き場はオブジェクトストレージです。",
      "explanation": "ロードバランサー→APIゲートウェイ→仮想ネットワーク→コンピュート→オブジェクトストレージの流れをイメージしましょう。"
    },
    "q2": {
      "hint": "デコイに紛らわしいサービスがありますが、層ごとの役割（入口／アプリ／ネットワーク／計算／データ）で選びましょう。",
      "explanation": "入口はLB、アプリ層の窓口はAPIゲートウェイ、ネットワークはVPC、計算はVM、データはオブジェクトストレージです。"
    },
    "q3": {
      "hint": "WAF・監視・ログなどのデコイは役割が違います。通信の入り口か、アプリの前口か、ネットワーク／計算／データのどれかで判別しましょう。",
      "explanation": "ロードバランサー→APIゲートウェイ→仮想ネットワーク→コンピュート→オブジェクトストレージの対応です。"
    }
  },
  "rankDescriptions": {
    "S": "完璧です。層ごとの役割で迷わず構成できています。",
    "A": "かなり良いです。細部の読み替えができています。",
    "B": "試行錯誤できています。層の対応をもう一段固めましょう。",
    "C": "基礎は掴めています。入口/アプリ/データの役割を整理してください。",
    "D": "もう一度解説動画を見て再チャレンジです。"
  }
}
